cloudmesh.evegenie-1.2.4.dist-info/DESCRIPTION.rst
cloudmesh.evegenie-1.2.4.dist-info/METADATA
cloudmesh.evegenie-1.2.4.dist-info/RECORD
cloudmesh.evegenie-1.2.4.dist-info/WHEEL
cloudmesh.evegenie-1.2.4.dist-info/entry_points.txt
cloudmesh.evegenie-1.2.4.dist-info/metadata.json
cloudmesh.evegenie-1.2.4.dist-info/top_level.txt
evegenie/__init__.py
evegenie/evegenie.py
evegenie/geneve.py
evegenie/templates/__init__.py
evegenie/templates/settings.py.j2
