Metadata-Version: 2.0
Name: cloudmesh.evegenie
Version: 1.2.4
Summary: A dynamic extensible CMD based command shell
Home-page: https://github.com/cloudmesh/evegenie
Author: frodopwns, ultimateboy, nicolaiarocci, laszewsk
Author-email: laszewski@gmail.com
License: Apache 2.0
Platform: UNKNOWN
Classifier: Development Status :: 5 - Production/Stable
Classifier: Environment :: Web Environment
Classifier: Intended Audience :: Developers
Classifier: License :: OSI Approved :: BSD License
Classifier: Operating System :: OS Independent
Classifier: Programming Language :: Python
Classifier: Programming Language :: Python :: 2
Classifier: Programming Language :: Python :: 3
Requires-Dist: docopt
Requires-Dist: eve
